component_tags/__init__.py
component_tags/apps.py
component_tags/tests.py
component_tags/template/__init__.py
component_tags/template/attributes.py
component_tags/template/builtins.py
component_tags/template/choices.py
component_tags/template/components.py
component_tags/template/context.py
component_tags/template/helpers.py
component_tags/template/library.py
component_tags/template/media.py
component_tags/template/nodes.py
component_tags/template/parser.py
component_tags/template/wrappers.py
component_tags/templates/component_tags/base.html
component_tags/templates/component_tags/slot.html
django_component_tags-0.0.6.1.dist-info/AUTHORS.rst
django_component_tags-0.0.6.1.dist-info/LICENSE.txt
django_component_tags-0.0.6.1.dist-info/METADATA
django_component_tags-0.0.6.1.dist-info/WHEEL
django_component_tags-0.0.6.1.dist-info/top_level.txt
django_component_tags-0.0.6.1.dist-info/RECORD
