Metadata-Version: 2.1
Name: django-component-tags
Version: 0.0.6.1
Summary: Create advanced HTML components using Django Tags.
Home-page: https://github.com/syse-i/django-component-tags
Author: David Sosa Valdes
Author-email: david.sosa.valdes@gmail.com
License: MIT
Project-URL: Documentation, https://github.com/syse-i/django-component-tags#description
Project-URL: Source, https://github.com/syse-i/django-component-tags
Project-URL: Changelog, https://github.com/syse-i/django-component-tags/blob/main/CHANGELOG.rst
Project-URL: Tracker, https://github.com/syse-i/django-component-tags/issues
Keywords: "django","component","tags","templatetags","template"
Platform: any
Classifier: Development Status :: 4 - Beta
Classifier: Programming Language :: Python
Classifier: Programming Language :: Python :: 3
Classifier: Programming Language :: Python :: 3.6
Classifier: Programming Language :: Python :: 3.7
Classifier: Programming Language :: Python :: 3.8
Classifier: Programming Language :: Python :: 3.9
Classifier: Framework :: Django
Classifier: Framework :: Django :: 2.2
Classifier: Framework :: Django :: 3.0
Classifier: Framework :: Django :: 3.1
Classifier: Framework :: Django
License-File: LICENSE.txt
License-File: AUTHORS.rst
Requires-Dist: django
Requires-Dist: importlib-metadata ; python_version < "3.8"
Provides-Extra: testing
Requires-Dist: setuptools ; extra == 'testing'
Requires-Dist: pytest ; extra == 'testing'
Requires-Dist: pytest-cov ; extra == 'testing'
Requires-Dist: pytest-django ; extra == 'testing'
